P5Canvas/P5Canvas.py
P5Canvas/__init__.py
P5Canvas-1.0.0.dist-info/METADATA
P5Canvas-1.0.0.dist-info/WHEEL
P5Canvas-1.0.0.dist-info/top_level.txt
P5Canvas-1.0.0.dist-info/RECORD
