Metadata-Version: 2.1
Name: P5Canvas
Version: 1.0.0
Summary: Helper Class for Using p5.js with PyScript.
Author: Uniras
Author-email: tkappeng@gmail.com
License: MIT License
Project-URL: Homepage, https://github.com/uniras/P5Canvas
Project-URL: Repository, https://github.com/uniras/P5Canvas
Keywords: PyScript,p5.js,Canvas,Processing
Classifier: Development Status :: 5 - Production/Stable
Classifier: Intended Audience :: Developers
Classifier: License :: OSI Approved :: MIT License
Classifier: Programming Language :: Python :: 3
Classifier: Programming Language :: Python :: 3.7
Classifier: Programming Language :: Python :: 3.8
Classifier: Programming Language :: Python :: 3.9
Classifier: Programming Language :: Python :: 3.10
Classifier: Programming Language :: Python :: 3 :: Only
Classifier: Topic :: Software Development :: Libraries
Classifier: Topic :: Software Development :: Libraries :: Python Modules
Classifier: Topic :: Utilities
